ts_cc_extractor/__init__.py
ts_cc_extractor/__main__.py
ts_cc_extractor/extractor.py
ts_cc_extractor/media_tools/__init__.py
ts_cc_extractor/media_tools/cea608.py
ts_cc_extractor/media_tools/cea708.py
ts_cc_extractor/media_tools/scc.py
ts_cc_extractor/media_tools/ts.py
ts_cc_extractor-0.0.3.dist-info/LICENSE
ts_cc_extractor-0.0.3.dist-info/METADATA
ts_cc_extractor-0.0.3.dist-info/WHEEL
ts_cc_extractor-0.0.3.dist-info/entry_points.txt
ts_cc_extractor-0.0.3.dist-info/top_level.txt
ts_cc_extractor-0.0.3.dist-info/RECORD
