Metadata-Version: 2.1
Name: ts-cc-extractor
Version: 0.0.3
Summary: Extract EIA-608 captions from Video Transport Stream (*.ts) fileand convert them to SubRip (*.srt) or Video Text Tracks (*.vtt) subtitles
Home-page: https://github.com/interlark/ts-cc-extractor
Author: Andy Trofimov
Author-email: interlark@gmail.com
License: BSD
Keywords: ts extract convert eia-608 srt vtt subtitles captions
Platform: UNKNOWN
Classifier: Topic :: Internet
Classifier: Topic :: Utilities
Classifier: Topic :: Multimedia :: Video
Classifier: Operating System :: OS Independent
Classifier: Programming Language :: Python :: 3 :: Only
Classifier: Programming Language :: Python :: 3.7
Classifier: Programming Language :: Python :: 3.8
Classifier: Programming Language :: Python :: 3.9
Classifier: Programming Language :: Python :: 3.10
Classifier: License :: OSI Approved :: BSD License
Requires-Python: >=3.7
Requires-Dist: pycaption (>=2.0.9)
Provides-Extra: dev
Requires-Dist: wheel (<0.38,>=0.36.2) ; extra == 'dev'
Requires-Dist: tox (<4,>=3.5) ; extra == 'dev'
Requires-Dist: pytest (<8,>=6.2) ; extra == 'dev'
Requires-Dist: typing-extensions (>=4.0.0) ; (python_version < "3.8") and extra == 'dev'
